dockernel/__init__.py
dockernel/__main__.py
dockernel/app.py
dockernel/kernelspec.py
dockernel/cli/__init__.py
dockernel/cli/install.py
dockernel/cli/main.py
dockernel/cli/start.py
dockernel-1.0.2.dist-info/LICENSE
dockernel-1.0.2.dist-info/METADATA
dockernel-1.0.2.dist-info/WHEEL
dockernel-1.0.2.dist-info/entry_points.txt
dockernel-1.0.2.dist-info/top_level.txt
dockernel-1.0.2.dist-info/RECORD
